flake8_report/__init__.py
flake8_report/flake8_error.py
flake8_report/reporters.py
flake8_report/version.py
flake8_report/formatters/__init__.py
flake8_report/formatters/checklist.py
flake8_report/formatters/codes_lookup.py
flake8_report/formatters/group_by.py
flake8_report/formatters/report.py
flake8_report/formatters/sorters.py
flake8_report/formatters/wiki.py
flake8_report/nightmare/__init__.py
flake8_report/nightmare/nightmare.py
flake8_report-0.1.0a1.dist-info/LICENSE
flake8_report-0.1.0a1.dist-info/METADATA
flake8_report-0.1.0a1.dist-info/WHEEL
flake8_report-0.1.0a1.dist-info/entry_points.txt
flake8_report-0.1.0a1.dist-info/top_level.txt
flake8_report-0.1.0a1.dist-info/RECORD
