Metadata-Version: 2.1
Name: flake8-report
Version: 0.1.0a1
Summary: JSON Formatting Reporter plugin for Flake8
Home-page: https://gitlab.com/pycqa/flake8-report
Author: Curtis Forrester
Author-email: curtis.forrester@gmail.com
License: MIT
Platform: UNKNOWN
Classifier: Development Status :: 5 - Production/Stable
Classifier: Environment :: Console
Classifier: Framework :: Flake8
Classifier: Intended Audience :: Developers
Classifier: License :: OSI Approved :: MIT License
Classifier: Programming Language :: Python
Classifier: Programming Language :: Python :: 3.7
Classifier: Topic :: Software Development :: Quality Assurance
Requires-Python: >=3.7
